pvrhino/LICENSE
pvrhino/__init__.py
pvrhino/_factory.py
pvrhino/_rhino.py
pvrhino/_util.py
pvrhino/lib/common/rhino_params.pv
pvrhino/lib/linux/x86_64/libpv_rhino.so
pvrhino/lib/mac/arm64/libpv_rhino.dylib
pvrhino/lib/mac/x86_64/libpv_rhino.dylib
pvrhino/lib/raspberry-pi/arm11/libpv_rhino.so
pvrhino/lib/raspberry-pi/cortex-a53/libpv_rhino.so
pvrhino/lib/raspberry-pi/cortex-a53-aarch64/libpv_rhino.so
pvrhino/lib/raspberry-pi/cortex-a72/libpv_rhino.so
pvrhino/lib/raspberry-pi/cortex-a72-aarch64/libpv_rhino.so
pvrhino/lib/raspberry-pi/cortex-a76/libpv_rhino.so
pvrhino/lib/raspberry-pi/cortex-a76-aarch64/libpv_rhino.so
pvrhino/lib/windows/amd64/libpv_rhino.dll
pvrhino/lib/windows/amd64/pv_ypu_impl_cuda.dll
pvrhino/lib/windows/arm64/libpv_rhino.dll
pvrhino-4.0.1.dist-info/METADATA
pvrhino-4.0.1.dist-info/WHEEL
pvrhino-4.0.1.dist-info/top_level.txt
pvrhino-4.0.1.dist-info/RECORD
